{
  "ok": false,
  "record": {
    "node_id": "",
    "node_name": "",
    "address": "",
    "public_key": "",
    "issued_at": "",
    "expires_at": "",
    "signature": ""
  },
  "service_record": {
    "node_id": "",
    "node_name": "",
    "service_name": "",
    "is_hidden": false,
    "public_key": "",
    "issued_at": "",
    "expires_at": "",
    "signature": ""
  },
  "records": [
    {
      "node_id": "vx6_a15ca70a841a1517",
      "node_name": "abhishek",
      "address": "[2401:4900:bbe1:a290:db82:d60b:639f:1571]:4242",
      "public_key": "rGBTeOnvGOZl+XJROOF3cRuLsZYjhgBhqY9wpPq9byU=",
      "issued_at": "2026-04-25T08:35:33Z",
      "expires_at": "2026-04-25T08:55:33Z",
      "signature": "t186kdqebfjBu80nXZRhIOZ0vZMoMlU4qO8l0POjFPnjP7TdA6z0bHh8BNsJY6BWGflm0ECr3Ngb0gaW+Ik0Dw=="
    },
    {
      "node_id": "vx6_9ad54204adc88894",
      "node_name": "asus",
      "address": "[2401:4900:bbe1:a290:c232:5900:6f64:fd35]:4242",
      "public_key": "H8MOfHm7kLRaXiZGkl4c72zqVBsluBRSOAG/jgGqazo=",
      "issued_at": "2026-04-25T08:35:29Z",
      "expires_at": "2026-04-25T08:55:29Z",
      "signature": "+J2gGGdeUP6PnmVtadfMqu6omJtc35UiMmcsWWfjsnD56in1x9BHwlAzUAtrAlWnYqzGrV7v/fW+0rnYLSgDDw=="
    },
    {
      "node_id": "vx6_8d609ee1f0b9839d",
      "node_name": "surya",
      "address": "[2401:4900:bbe1:a290:c232:5900:6f64:fd35]:4242",
      "public_key": "feXzxyEEgl9W353sLMD0pugk+t8k1nV/Ie4s2oHoJvA=",
      "issued_at": "2026-04-25T08:57:13Z",
      "expires_at": "2026-04-25T09:17:13Z",
      "signature": "zuxGzjWN4DZ6FoIbY5kWJ7uqehbfXTTmmmoibZkawoYvnSMFpui6vIc63Cp59mHFX56rOYEWVZ5Q+ikbL6E7BA=="
    }
  ],
  "service_records": [
    {
      "node_id": "vx6_a15ca70a841a1517",
      "node_name": "abhishek",
      "service_name": "don",
      "address": "[2401:4900:bbe1:a290:db82:d60b:639f:1571]:4242",
      "is_hidden": false,
      "public_key": "rGBTeOnvGOZl+XJROOF3cRuLsZYjhgBhqY9wpPq9byU=",
      "issued_at": "2026-04-25T08:35:33Z",
      "expires_at": "2026-04-25T08:55:33Z",
      "signature": "Wsl+9W7lgcR6oYtghBvo1qgqoRrvCyYEepGUKlZsPm6Z4cALmEK9WCkJd51e9bm2RqSl6+W6Dc1pbj4yHeXODA=="
    },
    {
      "node_id": "vx6_9ad54204adc88894",
      "node_name": "asus",
      "service_name": "hackitise",
      "address": "[2401:4900:bbe1:a290:c232:5900:6f64:fd35]:4242",
      "is_hidden": false,
      "public_key": "H8MOfHm7kLRaXiZGkl4c72zqVBsluBRSOAG/jgGqazo=",
      "issued_at": "2026-04-25T08:35:30Z",
      "expires_at": "2026-04-25T08:55:30Z",
      "signature": "Qo390ZBSfEWaLrhbMkIvNsiyM9aeqL/b2zpFwxh9kwV4zLKwEMJPRPG6XTkj0KYNhKQgKEIgGYLY6aL0tbLMDA=="
    },
    {
      "node_id": "vx6_9ad54204adc88894",
      "node_name": "asus",
      "service_name": "loooo",
      "address": "[2401:4900:bbe1:a290:c232:5900:6f64:fd35]:4242",
      "is_hidden": false,
      "public_key": "H8MOfHm7kLRaXiZGkl4c72zqVBsluBRSOAG/jgGqazo=",
      "issued_at": "2026-04-25T08:35:30Z",
      "expires_at": "2026-04-25T08:55:30Z",
      "signature": "m6tBPKMBi34rQ71m+wKsuTExSyN26e/TFBU9NbS0RA73e+WkaOwb74wyQGHopKtrZOoh+ey505XkUmh+ZiHFAg=="
    },
    {
      "node_id": "vx6_9ad54204adc88894",
      "node_name": "asus",
      "service_name": "py-serv",
      "address": "[2401:4900:bbe1:a290:c232:5900:6f64:fd35]:4242",
      "is_hidden": false,
      "public_key": "H8MOfHm7kLRaXiZGkl4c72zqVBsluBRSOAG/jgGqazo=",
      "issued_at": "2026-04-25T08:35:30Z",
      "expires_at": "2026-04-25T08:55:30Z",
      "signature": "nkHyrwDgdNsxTREG1fv6LhXoSYQMKOpiXydrMS3f/15gRvS1t1D66SQIP6q3owjwz8TyA06w/FauLKNb3G8dBg=="
    },
    {
      "node_id": "vx6_9ad54204adc88894",
      "node_name": "asus",
      "service_name": "ssh-hehe",
      "address": "[2401:4900:bbe1:a290:c232:5900:6f64:fd35]:4242",
      "is_hidden": false,
      "public_key": "H8MOfHm7kLRaXiZGkl4c72zqVBsluBRSOAG/jgGqazo=",
      "issued_at": "2026-04-25T08:35:30Z",
      "expires_at": "2026-04-25T08:55:30Z",
      "signature": "tQf8FpwRcG+3+BMNphjfUZ/Ck7Ad5wAiOt+xVHo90zGynLcpjXxXFEKTcULyHL2YVsA6Qc+ywUUNzy4KgswbDw=="
    },
    {
      "node_id": "vx6_9ad54204adc88894",
      "node_name": "asus",
      "service_name": "testtttt",
      "address": "[2401:4900:bbe1:a290:c232:5900:6f64:fd35]:4242",
      "is_hidden": false,
      "public_key": "H8MOfHm7kLRaXiZGkl4c72zqVBsluBRSOAG/jgGqazo=",
      "issued_at": "2026-04-25T08:35:30Z",
      "expires_at": "2026-04-25T08:55:30Z",
      "signature": "CO9BrrkxKIiFFaEjvrQDGRD48+c2EFSMTIFipGtyE8bXElx4CC1xR96Zvk59Qv1+v0lGblOylFJjbyi1pvziAw=="
    },
    {
      "node_id": "vx6_9ad54204adc88894",
      "node_name": "asus",
      "service_name": "tryin",
      "address": "[2401:4900:bbe1:a290:c232:5900:6f64:fd35]:4242",
      "is_hidden": false,
      "public_key": "H8MOfHm7kLRaXiZGkl4c72zqVBsluBRSOAG/jgGqazo=",
      "issued_at": "2026-04-25T08:35:30Z",
      "expires_at": "2026-04-25T08:55:30Z",
      "signature": "65J8BZIcwVCW/nre9ElVckvIjYHYuRL1gDzp5278/AYBLF40VbV4EhPHnlnq/i9H2bFlqZhLQ3AvRwKc6KqrAQ=="
    },
    {
      "node_id": "vx6_8d609ee1f0b9839d",
      "node_name": "surya",
      "service_name": "live-cam",
      "address": "[2401:4900:bbe1:a290:c232:5900:6f64:fd35]:4242",
      "is_hidden": false,
      "public_key": "feXzxyEEgl9W353sLMD0pugk+t8k1nV/Ie4s2oHoJvA=",
      "issued_at": "2026-04-25T08:57:15Z",
      "expires_at": "2026-04-25T09:17:15Z",
      "signature": "FoiZOM5678L+JbNVaIaapN5vQr8iwGq+anlXTfEatFPGjSvu3BcFwrrOw4tu9eKuIyqNUtecvJAWdbV7/l50BQ=="
    },
    {
      "node_id": "vx6_8d609ee1f0b9839d",
      "node_name": "surya",
      "service_name": "share",
      "address": "[2401:4900:bbe1:a290:c232:5900:6f64:fd35]:4242",
      "is_hidden": false,
      "public_key": "feXzxyEEgl9W353sLMD0pugk+t8k1nV/Ie4s2oHoJvA=",
      "issued_at": "2026-04-25T08:57:15Z",
      "expires_at": "2026-04-25T09:17:15Z",
      "signature": "nCQHQHjB60z787R/yCxgvxBONGhHBtWzHMZqzjGPBwQDgDrwMzkm2c5p3Y44ZXwRW/Qu2dNCE3CtGe3TFZBOAg=="
    },
    {
      "node_id": "vx6_8d609ee1f0b9839d",
      "node_name": "surya",
      "service_name": "v-share",
      "address": "[2401:4900:bbe1:a290:c232:5900:6f64:fd35]:4242",
      "is_hidden": false,
      "public_key": "feXzxyEEgl9W353sLMD0pugk+t8k1nV/Ie4s2oHoJvA=",
      "issued_at": "2026-04-25T08:57:15Z",
      "expires_at": "2026-04-25T09:17:15Z",
      "signature": "dlCUpQk+lkzhTsjQ9BjzShgbfkA/hihcndTBwbMEmN8hIKbxbvTrMoBDy1LsB7KqkijfMDckiicMNZnf+IH0AA=="
    },
    {
      "node_id": "vx6_8d609ee1f0b9839d",
      "node_name": "surya",
      "service_name": "web",
      "address": "[2401:4900:bbe1:a290:c232:5900:6f64:fd35]:4242",
      "is_hidden": false,
      "public_key": "feXzxyEEgl9W353sLMD0pugk+t8k1nV/Ie4s2oHoJvA=",
      "issued_at": "2026-04-25T08:57:15Z",
      "expires_at": "2026-04-25T09:17:15Z",
      "signature": "yUbazW5p9g3SZc5ooUS6TZ0wdryGaWL8iqq8kcSqA2uGYQH5wEr+q8ANYfETOzjYmzVRgN2onfA6NJS8Pjm0Cw=="
    }
  ]
}
